matchtext/__init__.py
matchtext/caseconversion.py
matchtext/runutils.py
matchtext/stringmatcher.py
matchtext/tokenmatcher.py
matchtext/utils.py
matchtext/ahocorapy/keywordtree.py
matchtext-0.2.3.dist-info/AUTHORS.rst
matchtext-0.2.3.dist-info/LICENSE
matchtext-0.2.3.dist-info/METADATA
matchtext-0.2.3.dist-info/WHEEL
matchtext-0.2.3.dist-info/top_level.txt
matchtext-0.2.3.dist-info/RECORD
