Metadata-Version: 2.1
Name: matchtext
Version: 0.2.3
Summary: Fast text/token matching and replacement
Home-page: https://github.com/johann-petrak/matchtext
Author: Johann Petrak
Author-email: johann.petrak@gmail.com
License: apache
Project-URL: Documentation, https://github.com/johann-petrak/matchtext
Platform: any
Classifier: License :: OSI Approved :: Apache Software License
Classifier: Development Status :: 3 - Alpha
Classifier: Programming Language :: Python :: 3
Classifier: Intended Audience :: Developers
Classifier: Topic :: Text Processing
Requires-Python: >=3.6
Provides-Extra: testing
Requires-Dist: pytest ; extra == 'testing'
Requires-Dist: pytest-cov ; extra == 'testing'
